[{"date8061": 1514280060000, "ohlcv": {"low": 29.16, "open": 29.21, "volume": 188.03066, "close": 29.18, "high": 29.25}}, {"date8061": 1514280120000, "ohlcv": {"low": 29.17, "open": 29.23, "volume": 342.11637, "close": 29.21, "high": 29.25}}, {"date8061": 1514280180000, "ohlcv": {"low": 29.15, "open": 29.15, "volume": 453.46486, "close": 29.19, "high": 29.21}}, {"date8061": 1514280240000, "ohlcv": {"low": 29.1, "open": 29.1, "volume": 496.96594, "close": 29.2, "high": 29.23}}, {"date8061": 1514280300000, "ohlcv": {"low": 29.17, "open": 29.18, "volume": 300.22051, "close": 29.23, "high": 29.28}}, {"date8061": 1514280360000, "ohlcv": {"low": 29.24, "open": 29.27, "volume": 351.21514, "close": 29.24, "high": 29.31}}, {"date8061": 1514280420000, "ohlcv": {"low": 29.16, "open": 29.24, "volume": 252.30497, "close": 29.19, "high": 29.24}}, {"date8061": 1514280480000, "ohlcv": {"low": 29.16, "open": 29.16, "volume": 277.70702, "close": 29.19, "high": 29.21}}, {"date8061": 1514280540000, "ohlcv": {"low": 29.15, "open": 29.17, "volume": 379.19687, "close": 29.17, "high": 29.19}}, {"date8061": 1514280600000, "ohlcv": {"low": 29.16, "open": 29.18, "volume": 433.52437, "close": 29.18, "high": 29.19}}, {"date8061": 1514280660000, "ohlcv": {"low": 29.15, "open": 29.18, "volume": 452.53425, "close": 29.15, "high": 29.21}}, {"date8061": 1514280720000, "ohlcv": {"low": 29.1, "open": 29.16, "volume": 364.16249, "close": 29.15, "high": 29.21}}, {"date8061": 1514280780000, "ohlcv": {"low": 29.15, "open": 29.15, "volume": 131.21, "close": 29.16, "high": 29.16}}, {"date8061": 1514280840000, "ohlcv": {"low": 29.15, "open": 29.17, "volume": 689.77043, "close": 29.2, "high": 29.2}}, {"date8061": 1514280960000, "ohlcv": {"low": 29.2, "open": 29.2, "volume": 675.61576, "close": 29.25, "high": 29.27}}, {"date8061": 1514281020000, "ohlcv": {"low": 29.2, "open": 29.25, "volume": 579.90657, "close": 29.2, "high": 29.32}}, {"date8061": 1514281080000, "ohlcv": {"low": 29.21, "open": 29.21, "volume": 521.26687, "close": 29.4, "high": 29.4}}, {"date8061": 1514281140000, "ohlcv": {"low": 29.26, "open": 29.31, "volume": 409.09206, "close": 29.28, "high": 29.4}}, {"date8061": 1514281200000, "ohlcv": {"low": 29.27, "open": 29.31, "volume": 268.96471, "close": 29.3, "high": 29.31}}, {"date8061": 1514281260000, "ohlcv": {"low": 29.27, "open": 29.27, "volume": 292.8908, "close": 29.29, "high": 29.35}}, {"date8061": 1514281320000, "ohlcv": {"low": 29.23, "open": 29.35, "volume": 357.40831, "close": 29.41, "high": 29.41}}, {"date8061": 1514281380000, "ohlcv": {"low": 29.31, "open": 29.31, "volume": 190.76, "close": 29.41, "high": 29.41}}, {"date8061": 1514281440000, "ohlcv": {"low": 29.3, "open": 29.42, "volume": 190.925, "close": 29.3, "high": 29.42}}, {"date8061": 1514281500000, "ohlcv": {"low": 29.23, "open": 29.36, "volume": 225.28663, "close": 29.37, "high": 29.41}}, {"date8061": 1514281560000, "ohlcv": {"low": 29.34, "open": 29.34, "volume": 52.18596, "close": 29.36, "high": 29.36}}, {"date8061": 1514281620000, "ohlcv": {"low": 29.4, "open": 29.4, "volume": 2.32263, "close": 29.43, "high": 29.43}}, {"date8061": 1514281680000, "ohlcv": {"low": 29.42, "open": 29.45, "volume": 441.74375, "close": 29.45, "high": 29.45}}, {"date8061": 1514281740000, "ohlcv": {"low": 29.5, "open": 29.5, "volume": 51.33, "close": 29.5, "high": 29.5}}, {"date8061": 1514281800000, "ohlcv": {"low": 29.48, "open": 29.48, "volume": 105.36092, "close": 29.64, "high": 29.64}}, {"date8061": 1514281860000, "ohlcv": {"low": 29.63, "open": 29.63, "volume": 60.06001, "close": 29.63, "high": 29.63}}, {"date8061": 1514281920000, "ohlcv": {"low": 29.42, "open": 29.63, "volume": 6020.72699, "close": 29.5, "high": 29.63}}, {"date8061": 1514281980000, "ohlcv": {"low": 29.47, "open": 29.54, "volume": 607.65526, "close": 29.5, "high": 29.55}}, {"date8061": 1514282040000, "ohlcv": {"low": 29.44, "open": 29.52, "volume": 566.47927, "close": 29.45, "high": 29.52}}, {"date8061": 1514282100000, "ohlcv": {"low": 29.44, "open": 29.44, "volume": 472.62462, "close": 29.46, "high": 29.46}}, {"date8061": 1514282160000, "ohlcv": {"low": 29.41, "open": 29.43, "volume": 190.34947, "close": 29.43, "high": 29.43}}, {"date8061": 1514282220000, "ohlcv": {"low": 29.38, "open": 29.4, "volume": 1589.51122, "close": 29.39, "high": 29.43}}, {"date8061": 1514282280000, "ohlcv": {"low": 29.43, "open": 29.44, "volume": 2205.08687, "close": 29.43, "high": 29.67}}, {"date8061": 1514282340000, "ohlcv": {"low": 29.41, "open": 29.44, "volume": 909.2633, "close": 29.42, "high": 29.49}}, {"date8061": 1514282400000, "ohlcv": {"low": 29.38, "open": 29.39, "volume": 575.45203, "close": 29.46, "high": 29.49}}, {"date8061": 1514282460000, "ohlcv": {"low": 29.39, "open": 29.49, "volume": 426.58503, "close": 29.4, "high": 29.54}}, {"date8061": 1514282520000, "ohlcv": {"low": 29.4, "open": 29.43, "volume": 490.28358, "close": 29.53, "high": 29.56}}, {"date8061": 1514282580000, "ohlcv": {"low": 29.5, "open": 29.56, "volume": 416.61713, "close": 29.6, "high": 29.62}}, {"date8061": 1514282640000, "ohlcv": {"low": 29.51, "open": 29.62, "volume": 126.45487, "close": 29.6, "high": 29.62}}, {"date8061": 1514282760000, "ohlcv": {"low": 29.53, "open": 29.55, "volume": 353.96892, "close": 29.53, "high": 29.55}}, {"date8061": 1514282820000, "ohlcv": {"low": 29.49, "open": 29.52, "volume": 1345.88987, "close": 29.49, "high": 29.52}}, {"date8061": 1514282940000, "ohlcv": {"low": 29.44, "open": 29.46, "volume": 1156.23858, "close": 29.45, "high": 29.46}}, {"date8061": 1514283000000, "ohlcv": {"low": 29.44, "open": 29.45, "volume": 420.87962, "close": 29.45, "high": 29.45}}, {"date8061": 1514283120000, "ohlcv": {"low": 29.39, "open": 29.39, "volume": 49.28703, "close": 29.39, "high": 29.39}}, {"date8061": 1514283180000, "ohlcv": {"low": 29.48, "open": 29.48, "volume": 1740.79538, "close": 29.51, "high": 29.51}}, {"date8061": 1514283240000, "ohlcv": {"low": 29.45, "open": 29.45, "volume": 150.04775, "close": 29.45, "high": 29.45}}, {"date8061": 1514283360000, "ohlcv": {"low": 29.5, "open": 29.5, "volume": 5.9295, "close": 29.5, "high": 29.5}}, {"date8061": 1514283420000, "ohlcv": {"low": 29.5, "open": 29.5, "volume": 516.191, "close": 29.5, "high": 29.5}}, {"date8061": 1514283540000, "ohlcv": {"low": 29.41, "open": 29.5, "volume": 2265.93668, "close": 29.44, "high": 29.5}}, {"date8061": 1514283600000, "ohlcv": {"low": 29.38, "open": 29.4, "volume": 903.92684, "close": 29.38, "high": 29.44}}, {"date8061": 1514283660000, "ohlcv": {"low": 29.37, "open": 29.4, "volume": 576.28277, "close": 29.38, "high": 29.44}}, {"date8061": 1514283720000, "ohlcv": {"low": 29.37, "open": 29.4, "volume": 358.09906, "close": 29.38, "high": 29.42}}, {"date8061": 1514283840000, "ohlcv": {"low": 29.37, "open": 29.37, "volume": 650.95668, "close": 29.37, "high": 29.37}}, {"date8061": 1514283900000, "ohlcv": {"low": 29.38, "open": 29.38, "volume": 1592.529, "close": 29.38, "high": 29.44}}, {"date8061": 1514283960000, "ohlcv": {"low": 29.38, "open": 29.42, "volume": 148.09406, "close": 29.4, "high": 29.43}}, {"date8061": 1514284020000, "ohlcv": {"low": 29.38, "open": 29.42, "volume": 353.14908, "close": 29.39, "high": 29.45}}, {"date8061": 1514284080000, "ohlcv": {"low": 29.37, "open": 29.39, "volume": 192.33572, "close": 29.37, "high": 29.39}}, {"date8061": 1514284140000, "ohlcv": {"low": 29.32, "open": 29.37, "volume": 158.76383, "close": 29.38, "high": 29.39}}, {"date8061": 1514284380000, "ohlcv": {"low": 29.37, "open": 29.37, "volume": 411.50667, "close": 29.38, "high": 29.38}}, {"date8061": 1514284500000, "ohlcv": {"low": 29.43, "open": 29.45, "volume": 3098.47569, "close": 29.44, "high": 29.45}}, {"date8061": 1514284560000, "ohlcv": {"low": 29.39, "open": 29.42, "volume": 160.70273, "close": 29.39, "high": 29.42}}, {"date8061": 1514284620000, "ohlcv": {"low": 29.32, "open": 29.38, "volume": 431.86502, "close": 29.44, "high": 29.44}}, {"date8061": 1514284740000, "ohlcv": {"low": 29.5, "open": 29.5, "volume": 58.5575, "close": 29.5, "high": 29.5}}, {"date8061": 1514284800000, "ohlcv": {"low": 29.38, "open": 29.44, "volume": 720.59185, "close": 29.38, "high": 29.44}}, {"date8061": 1514284860000, "ohlcv": {"low": 29.33, "open": 29.38, "volume": 2205.94099, "close": 29.33, "high": 29.39}}, {"date8061": 1514284980000, "ohlcv": {"low": 29.41, "open": 29.41, "volume": 147.16776, "close": 29.44, "high": 29.44}}, {"date8061": 1514285160000, "ohlcv": {"low": 29.48, "open": 29.49, "volume": 2404.7835, "close": 29.53, "high": 29.54}}, {"date8061": 1514285220000, "ohlcv": {"low": 29.45, "open": 29.48, "volume": 396.82522, "close": 29.45, "high": 29.54}}, {"date8061": 1514285280000, "ohlcv": {"low": 29.42, "open": 29.57, "volume": 165.84631, "close": 29.5, "high": 29.57}}, {"date8061": 1514285340000, "ohlcv": {"low": 29.41, "open": 29.56, "volume": 288.48679, "close": 29.55, "high": 29.56}}, {"date8061": 1514285400000, "ohlcv": {"low": 29.44, "open": 29.49, "volume": 426.56555, "close": 29.55, "high": 29.55}}, {"date8061": 1514285460000, "ohlcv": {"low": 29.48, "open": 29.52, "volume": 259.85128, "close": 29.52, "high": 29.54}}, {"date8061": 1514285520000, "ohlcv": {"low": 29.44, "open": 29.51, "volume": 382.40159, "close": 29.45, "high": 29.55}}, {"date8061": 1514285580000, "ohlcv": {"low": 29.36, "open": 29.44, "volume": 180.2774, "close": 29.43, "high": 29.47}}, {"date8061": 1514285640000, "ohlcv": {"low": 29.4, "open": 29.42, "volume": 223.78173, "close": 29.4, "high": 29.43}}, {"date8061": 1514285700000, "ohlcv": {"low": 29.38, "open": 29.43, "volume": 519.0016, "close": 29.4, "high": 29.43}}, {"date8061": 1514285760000, "ohlcv": {"low": 29.33, "open": 29.41, "volume": 336.43792, "close": 29.43, "high": 29.43}}, {"date8061": 1514285820000, "ohlcv": {"low": 29.38, "open": 29.4, "volume": 410.80583, "close": 29.38, "high": 29.42}}, {"date8061": 1514285880000, "ohlcv": {"low": 29.33, "open": 29.38, "volume": 162.22126, "close": 29.39, "high": 29.39}}, {"date8061": 1514285940000, "ohlcv": {"low": 29.38, "open": 29.38, "volume": 167.82902, "close": 29.43, "high": 29.52}}, {"date8061": 1514286000000, "ohlcv": {"low": 29.41, "open": 29.43, "volume": 189.06517, "close": 29.43, "high": 29.44}}, {"date8061": 1514286060000, "ohlcv": {"low": 29.37, "open": 29.43, "volume": 405.81891, "close": 29.39, "high": 29.43}}, {"date8061": 1514286120000, "ohlcv": {"low": 29.37, "open": 29.37, "volume": 226.47492, "close": 29.41, "high": 29.45}}, {"date8061": 1514286180000, "ohlcv": {"low": 29.37, "open": 29.38, "volume": 195.68828, "close": 29.39, "high": 29.43}}, {"date8061": 1514286240000, "ohlcv": {"low": 29.32, "open": 29.38, "volume": 147.48288, "close": 29.43, "high": 29.43}}, {"date8061": 1514286300000, "ohlcv": {"low": 29.4, "open": 29.44, "volume": 158.06538, "close": 29.43, "high": 29.45}}, {"date8061": 1514286360000, "ohlcv": {"low": 29.26, "open": 29.42, "volume": 157.63554, "close": 29.36, "high": 29.42}}, {"date8061": 1514286420000, "ohlcv": {"low": 29.32, "open": 29.32, "volume": 138.26764, "close": 29.32, "high": 29.34}}, {"date8061": 1514286480000, "ohlcv": {"low": 29.23, "open": 29.33, "volume": 164.28257, "close": 29.31, "high": 29.33}}, {"date8061": 1514286840000, "ohlcv": {"low": 29.2, "open": 29.25, "volume": 1164.74841, "close": 29.25, "high": 29.26}}, {"date8061": 1514286900000, "ohlcv": {"low": 29.25, "open": 29.26, "volume": 2327.55448, "close": 29.26, "high": 29.26}}, {"date8061": 1514286960000, "ohlcv": {"low": 29.2, "open": 29.26, "volume": 405.95634, "close": 29.25, "high": 29.27}}, {"date8061": 1514287020000, "ohlcv": {"low": 29.18, "open": 29.24, "volume": 256.25867, "close": 29.23, "high": 29.26}}, {"date8061": 1514287080000, "ohlcv": {"low": 29.1, "open": 29.13, "volume": 547.46515, "close": 29.13, "high": 29.22}}, {"date8061": 1514287140000, "ohlcv": {"low": 28.87, "open": 29.07, "volume": 1541.2919, "close": 28.88, "high": 29.09}}, {"date8061": 1514287200000, "ohlcv": {"low": 28.88, "open": 28.88, "volume": 122.22018, "close": 28.9, "high": 28.9}}, {"date8061": 1514287260000, "ohlcv": {"low": 28.96, "open": 28.96, "volume": 0.05798, "close": 29.02, "high": 29.02}}, {"date8061": 1514287320000, "ohlcv": {"low": 28.92, "open": 28.92, "volume": 408.61068, "close": 28.92, "high": 28.92}}, {"date8061": 1514287560000, "ohlcv": {"low": 28.91, "open": 28.91, "volume": 1632.43206, "close": 28.91, "high": 28.91}}, {"date8061": 1514287680000, "ohlcv": {"low": 28.89, "open": 28.89, "volume": 8.667, "close": 28.89, "high": 28.89}}, {"date8061": 1514287800000, "ohlcv": {"low": 28.83, "open": 28.83, "volume": 14.15553, "close": 28.83, "high": 28.83}}, {"date8061": 1514288220000, "ohlcv": {"low": 28.85, "open": 28.85, "volume": 0.08655, "close": 28.85, "high": 28.85}}, {"date8061": 1514288280000, "ohlcv": {"low": 28.93, "open": 28.93, "volume": 499.50538, "close": 28.93, "high": 28.93}}, {"date8061": 1514288340000, "ohlcv": {"low": 28.96, "open": 28.96, "volume": 649.58238, "close": 28.99, "high": 28.99}}, {"date8061": 1514288580000, "ohlcv": {"low": 28.91, "open": 28.91, "volume": 0.05782, "close": 28.91, "high": 28.91}}, {"date8061": 1514288640000, "ohlcv": {"low": 29.01, "open": 29.01, "volume": 0.02901, "close": 29.01, "high": 29.01}}, {"date8061": 1514288700000, "ohlcv": {"low": 29.0, "open": 29.06, "volume": 1080.94178, "close": 29.0, "high": 29.06}}, {"date8061": 1514288760000, "ohlcv": {"low": 28.99, "open": 28.99, "volume": 1.21758, "close": 28.99, "high": 28.99}}, {"date8061": 1514289000000, "ohlcv": {"low": 28.99, "open": 28.99, "volume": 0.17394, "close": 28.99, "high": 28.99}}, {"date8061": 1514289060000, "ohlcv": {"low": 29.09, "open": 29.09, "volume": 146.08998, "close": 29.09, "high": 29.09}}, {"date8061": 1514289180000, "ohlcv": {"low": 29.04, "open": 29.04, "volume": 780.94368, "close": 29.04, "high": 29.04}}, {"date8061": 1514289240000, "ohlcv": {"low": 28.97, "open": 28.97, "volume": 14.485, "close": 28.97, "high": 28.97}}, {"date8061": 1514289300000, "ohlcv": {"low": 28.96, "open": 28.96, "volume": 23.25488, "close": 28.96, "high": 28.96}}, {"date8061": 1514289360000, "ohlcv": {"low": 28.96, "open": 28.96, "volume": 39.06704, "close": 28.96, "high": 28.96}}, {"date8061": 1514289420000, "ohlcv": {"low": 28.97, "open": 28.97, "volume": 126.8886, "close": 28.97, "high": 28.97}}, {"date8061": 1514289480000, "ohlcv": {"low": 28.96, "open": 28.96, "volume": 15.29088, "close": 28.96, "high": 28.96}}, {"date8061": 1514289660000, "ohlcv": {"low": 28.9, "open": 28.9, "volume": 169.354, "close": 28.9, "high": 28.9}}, {"date8061": 1514289720000, "ohlcv": {"low": 28.91, "open": 28.92, "volume": 765.91559, "close": 28.91, "high": 28.92}}, {"date8061": 1514290080000, "ohlcv": {"low": 28.93, "open": 28.93, "volume": 0.02893, "close": 28.93, "high": 28.93}}, {"date8061": 1514290140000, "ohlcv": {"low": 28.92, "open": 28.92, "volume": 17.352, "close": 28.92, "high": 28.92}}, {"date8061": 1514290200000, "ohlcv": {"low": 28.87, "open": 28.87, "volume": 69.6017, "close": 28.92, "high": 28.92}}, {"date8061": 1514290260000, "ohlcv": {"low": 28.92, "open": 28.92, "volume": 14.46, "close": 28.92, "high": 28.92}}, {"date8061": 1514290320000, "ohlcv": {"low": 28.9, "open": 28.95, "volume": 43.38, "close": 28.9, "high": 28.95}}, {"date8061": 1514290380000, "ohlcv": {"low": 28.85, "open": 28.85, "volume": 0.02885, "close": 28.85, "high": 28.85}}, {"date8061": 1514290440000, "ohlcv": {"low": 28.73, "open": 28.73, "volume": 0.08619, "close": 28.73, "high": 28.73}}, {"date8061": 1514290500000, "ohlcv": {"low": 28.76, "open": 28.76, "volume": 328.18036, "close": 28.76, "high": 28.76}}, {"date8061": 1514290560000, "ohlcv": {"low": 28.8, "open": 28.8, "volume": 155.80986, "close": 28.86, "high": 28.86}}, {"date8061": 1514290680000, "ohlcv": {"low": 28.65, "open": 28.7, "volume": 302.645, "close": 28.65, "high": 28.7}}, {"date8061": 1514290740000, "ohlcv": {"low": 28.68, "open": 28.68, "volume": 3645.98295, "close": 28.68, "high": 28.69}}, {"date8061": 1514290800000, "ohlcv": {"low": 28.68, "open": 28.68, "volume": 28.685, "close": 28.69, "high": 28.69}}, {"date8061": 1514290860000, "ohlcv": {"low": 28.64, "open": 28.64, "volume": 62.23472, "close": 28.64, "high": 28.64}}, {"date8061": 1514290920000, "ohlcv": {"low": 28.64, "open": 28.64, "volume": 33.96704, "close": 28.64, "high": 28.64}}, {"date8061": 1514290980000, "ohlcv": {"low": 28.65, "open": 28.65, "volume": 0.02865, "close": 28.65, "high": 28.65}}, {"date8061": 1514291040000, "ohlcv": {"low": 28.67, "open": 28.67, "volume": 0.0861, "close": 28.73, "high": 28.73}}, {"date8061": 1514291100000, "ohlcv": {"low": 28.79, "open": 28.79, "volume": 0.02879, "close": 28.79, "high": 28.79}}, {"date8061": 1514291160000, "ohlcv": {"low": 28.87, "open": 28.87, "volume": 377.24429, "close": 28.87, "high": 28.87}}, {"date8061": 1514291460000, "ohlcv": {"low": 28.89, "open": 28.89, "volume": 0.05778, "close": 28.89, "high": 28.89}}, {"date8061": 1514291520000, "ohlcv": {"low": 28.93, "open": 28.93, "volume": 19.81705, "close": 28.93, "high": 28.93}}, {"date8061": 1514291580000, "ohlcv": {"low": 28.9, "open": 28.92, "volume": 262.92844, "close": 28.9, "high": 28.92}}, {"date8061": 1514291640000, "ohlcv": {"low": 28.88, "open": 28.89, "volume": 52.59915, "close": 28.88, "high": 28.89}}, {"date8061": 1514291700000, "ohlcv": {"low": 28.88, "open": 28.88, "volume": 66.88608, "close": 28.88, "high": 28.88}}, {"date8061": 1514291760000, "ohlcv": {"low": 28.93, "open": 28.93, "volume": 0.02893, "close": 28.93, "high": 28.93}}, {"date8061": 1514291820000, "ohlcv": {"low": 28.99, "open": 28.99, "volume": 17.394, "close": 28.99, "high": 28.99}}, {"date8061": 1514291880000, "ohlcv": {"low": 29.05, "open": 29.05, "volume": 0.02905, "close": 29.05, "high": 29.05}}, {"date8061": 1514291940000, "ohlcv": {"low": 28.94, "open": 28.94, "volume": 1157.97983, "close": 29.08, "high": 29.1}}, {"date8061": 1514292000000, "ohlcv": {"low": 29.11, "open": 29.11, "volume": 0.02911, "close": 29.11, "high": 29.11}}, {"date8061": 1514292060000, "ohlcv": {"low": 29.08, "open": 29.09, "volume": 339.95562, "close": 29.08, "high": 29.09}}, {"date8061": 1514292120000, "ohlcv": {"low": 29.09, "open": 29.09, "volume": 119.12355, "close": 29.09, "high": 29.09}}, {"date8061": 1514292300000, "ohlcv": {"low": 29.09, "open": 29.09, "volume": 6.57434, "close": 29.09, "high": 29.09}}, {"date8061": 1514292360000, "ohlcv": {"low": 29.11, "open": 29.11, "volume": 0.02911, "close": 29.11, "high": 29.11}}, {"date8061": 1514292480000, "ohlcv": {"low": 29.09, "open": 29.09, "volume": 14.545, "close": 29.09, "high": 29.09}}, {"date8061": 1514292720000, "ohlcv": {"low": 29.03, "open": 29.03, "volume": 0.14515, "close": 29.03, "high": 29.03}}, {"date8061": 1514293260000, "ohlcv": {"low": 29.07, "open": 29.07, "volume": 0.08721, "close": 29.07, "high": 29.07}}, {"date8061": 1514293320000, "ohlcv": {"low": 29.07, "open": 29.07, "volume": 301.92102, "close": 29.07, "high": 29.07}}, {"date8061": 1514293380000, "ohlcv": {"low": 29.1, "open": 29.1, "volume": 602.37, "close": 29.1, "high": 29.1}}, {"date8061": 1514293440000, "ohlcv": {"low": 29.1, "open": 29.1, "volume": 1976.9667, "close": 29.1, "high": 29.1}}, {"date8061": 1514293500000, "ohlcv": {"low": 29.21, "open": 29.22, "volume": 45.05212, "close": 29.21, "high": 29.22}}, {"date8061": 1514293620000, "ohlcv": {"low": 29.21, "open": 29.21, "volume": 86.02345, "close": 29.21, "high": 29.21}}, {"date8061": 1514293680000, "ohlcv": {"low": 29.21, "open": 29.21, "volume": 1870.07112, "close": 29.22, "high": 29.23}}, {"date8061": 1514293740000, "ohlcv": {"low": 29.21, "open": 29.25, "volume": 314.72329, "close": 29.21, "high": 29.25}}, {"date8061": 1514293800000, "ohlcv": {"low": 29.21, "open": 29.21, "volume": 25.79243, "close": 29.21, "high": 29.21}}, {"date8061": 1514293860000, "ohlcv": {"low": 29.22, "open": 29.24, "volume": 34.6942, "close": 29.22, "high": 29.24}}, {"date8061": 1514293920000, "ohlcv": {"low": 29.21, "open": 29.21, "volume": 0.11684, "close": 29.21, "high": 29.21}}, {"date8061": 1514294040000, "ohlcv": {"low": 29.16, "open": 29.16, "volume": 55.404, "close": 29.16, "high": 29.16}}, {"date8061": 1514294100000, "ohlcv": {"low": 29.09, "open": 29.16, "volume": 1286.41484, "close": 29.09, "high": 29.16}}, {"date8061": 1514294160000, "ohlcv": {"low": 29.05, "open": 29.1, "volume": 394.76855, "close": 29.08, "high": 29.1}}, {"date8061": 1514294220000, "ohlcv": {"low": 29.06, "open": 29.06, "volume": 171.62343, "close": 29.16, "high": 29.16}}, {"date8061": 1514294280000, "ohlcv": {"low": 29.07, "open": 29.09, "volume": 271.38383, "close": 29.08, "high": 29.13}}, {"date8061": 1514294340000, "ohlcv": {"low": 29.05, "open": 29.05, "volume": 107.80455, "close": 29.05, "high": 29.05}}, {"date8061": 1514294400000, "ohlcv": {"low": 29.05, "open": 29.05, "volume": 41.51245, "close": 29.05, "high": 29.05}}, {"date8061": 1514294460000, "ohlcv": {"low": 29.06, "open": 29.06, "volume": 462.25742, "close": 29.06, "high": 29.06}}, {"date8061": 1514294520000, "ohlcv": {"low": 29.05, "open": 29.05, "volume": 169.84957, "close": 29.06, "high": 29.06}}, {"date8061": 1514294580000, "ohlcv": {"low": 29.0, "open": 29.0, "volume": 58.0, "close": 29.0, "high": 29.0}}, {"date8061": 1514294700000, "ohlcv": {"low": 28.93, "open": 28.93, "volume": 98.44879, "close": 28.93, "high": 28.93}}, {"date8061": 1514294760000, "ohlcv": {"low": 28.93, "open": 28.96, "volume": 96.30533, "close": 28.93, "high": 28.96}}, {"date8061": 1514294820000, "ohlcv": {"low": 28.93, "open": 28.93, "volume": 186.71791, "close": 28.93, "high": 28.98}}, {"date8061": 1514294940000, "ohlcv": {"low": 28.9, "open": 28.9, "volume": 8.4388, "close": 28.9, "high": 28.9}}, {"date8061": 1514295000000, "ohlcv": {"low": 28.9, "open": 28.9, "volume": 3357.5731, "close": 28.9, "high": 28.9}}, {"date8061": 1514295060000, "ohlcv": {"low": 28.88, "open": 28.9, "volume": 2149.0117, "close": 28.88, "high": 28.92}}, {"date8061": 1514295120000, "ohlcv": {"low": 28.85, "open": 28.91, "volume": 144.76321, "close": 28.91, "high": 28.92}}, {"date8061": 1514295180000, "ohlcv": {"low": 28.97, "open": 28.99, "volume": 122.00009, "close": 28.97, "high": 29.09}}, {"date8061": 1514295240000, "ohlcv": {"low": 28.95, "open": 28.95, "volume": 283.82083, "close": 29.04, "high": 29.05}}, {"date8061": 1514295300000, "ohlcv": {"low": 28.92, "open": 28.94, "volume": 533.52559, "close": 28.92, "high": 29.16}}, {"date8061": 1514295360000, "ohlcv": {"low": 28.93, "open": 28.98, "volume": 302.24607, "close": 28.93, "high": 28.98}}, {"date8061": 1514295420000, "ohlcv": {"low": 28.86, "open": 28.93, "volume": 121.32042, "close": 28.86, "high": 28.93}}, {"date8061": 1514295480000, "ohlcv": {"low": 28.94, "open": 28.94, "volume": 210.13334, "close": 28.94, "high": 28.94}}, {"date8061": 1514295540000, "ohlcv": {"low": 28.97, "open": 28.97, "volume": 302.62062, "close": 28.97, "high": 28.97}}, {"date8061": 1514295600000, "ohlcv": {"low": 28.95, "open": 28.95, "volume": 60.93975, "close": 28.95, "high": 28.95}}, {"date8061": 1514295660000, "ohlcv": {"low": 28.94, "open": 28.94, "volume": 45.75414, "close": 28.94, "high": 28.94}}, {"date8061": 1514295720000, "ohlcv": {"low": 28.95, "open": 28.95, "volume": 15.77775, "close": 28.95, "high": 28.95}}, {"date8061": 1514295780000, "ohlcv": {"low": 29.0, "open": 29.0, "volume": 58.0, "close": 29.0, "high": 29.0}}, {"date8061": 1514295840000, "ohlcv": {"low": 29.0, "open": 29.0, "volume": 137.46, "close": 29.0, "high": 29.0}}, {"date8061": 1514295900000, "ohlcv": {"low": 28.93, "open": 28.93, "volume": 206.58913, "close": 28.93, "high": 28.93}}, {"date8061": 1514296020000, "ohlcv": {"low": 29.0, "open": 29.0, "volume": 4209.36732, "close": 29.12, "high": 29.12}}, {"date8061": 1514296080000, "ohlcv": {"low": 29.12, "open": 29.12, "volume": 303.95456, "close": 29.12, "high": 29.12}}, {"date8061": 1514296140000, "ohlcv": {"low": 29.12, "open": 29.12, "volume": 606.30752, "close": 29.12, "high": 29.12}}, {"date8061": 1514296200000, "ohlcv": {"low": 29.12, "open": 29.12, "volume": 664.8096, "close": 29.12, "high": 29.12}}, {"date8061": 1514296260000, "ohlcv": {"low": 29.12, "open": 29.12, "volume": 11.648, "close": 29.12, "high": 29.12}}, {"date8061": 1514296320000, "ohlcv": {"low": 29.12, "open": 29.12, "volume": 302.76064, "close": 29.12, "high": 29.12}}, {"date8061": 1514296380000, "ohlcv": {"low": 29.12, "open": 29.12, "volume": 361.088, "close": 29.12, "high": 29.12}}, {"date8061": 1514296440000, "ohlcv": {"low": 29.03, "open": 29.03, "volume": 2599.15427, "close": 29.04, "high": 29.04}}, {"date8061": 1514296500000, "ohlcv": {"low": 29.06, "open": 29.06, "volume": 29.07, "close": 29.08, "high": 29.08}}, {"date8061": 1514296560000, "ohlcv": {"low": 28.99, "open": 28.99, "volume": 52.44291, "close": 28.99, "high": 28.99}}, {"date8061": 1514296620000, "ohlcv": {"low": 29.08, "open": 29.08, "volume": 16.69192, "close": 29.08, "high": 29.08}}, {"date8061": 1514296680000, "ohlcv": {"low": 29.13, "open": 29.13, "volume": 58.72608, "close": 29.13, "high": 29.13}}, {"date8061": 1514296740000, "ohlcv": {"low": 29.09, "open": 29.09, "volume": 141.58103, "close": 29.09, "high": 29.09}}, {"date8061": 1514296800000, "ohlcv": {"low": 29.08, "open": 29.08, "volume": 17.47708, "close": 29.08, "high": 29.08}}, {"date8061": 1514296860000, "ohlcv": {"low": 29.13, "open": 29.13, "volume": 35.21817, "close": 29.13, "high": 29.13}}, {"date8061": 1514296920000, "ohlcv": {"low": 29.01, "open": 29.01, "volume": 145.31109, "close": 29.01, "high": 29.01}}, {"date8061": 1514296980000, "ohlcv": {"low": 29.07, "open": 29.07, "volume": 236.74608, "close": 29.07, "high": 29.07}}, {"date8061": 1514297040000, "ohlcv": {"low": 29.1, "open": 29.1, "volume": 95.3898, "close": 29.1, "high": 29.1}}, {"date8061": 1514297100000, "ohlcv": {"low": 29.05, "open": 29.05, "volume": 59.0894, "close": 29.09, "high": 29.09}}, {"date8061": 1514297160000, "ohlcv": {"low": 29.08, "open": 29.08, "volume": 26.66636, "close": 29.08, "high": 29.08}}, {"date8061": 1514297220000, "ohlcv": {"low": 29.06, "open": 29.1, "volume": 35.5111, "close": 29.06, "high": 29.1}}, {"date8061": 1514298600000, "ohlcv": {"low": 29.32, "open": 29.46, "volume": 321.8778, "close": 29.32, "high": 29.46}}, {"date8061": 1514300340000, "ohlcv": {"low": 29.06, "open": 29.06, "volume": 22.60868, "close": 29.06, "high": 29.06}}, {"date8061": 1514300400000, "ohlcv": {"low": 29.06, "open": 29.06, "volume": 17.0001, "close": 29.06, "high": 29.06}}, {"date8061": 1514300460000, "ohlcv": {"low": 29.0, "open": 29.01, "volume": 729.10599, "close": 29.0, "high": 29.01}}]